otlmow_modelbuilder/AbstractDatatypeCreator.py
otlmow_modelbuilder/DatatypeBuilderFunctions.py
otlmow_modelbuilder/GenericBuilderFunctions.py
otlmow_modelbuilder/GeometrieArtefactCollector.py
otlmow_modelbuilder/GeometrieInMemoryCreator.py
otlmow_modelbuilder/GeometrieInheritanceProcessor.py
otlmow_modelbuilder/GeometrieType.py
otlmow_modelbuilder/HelperFunctions.py
otlmow_modelbuilder/LegacyClassCreator.py
otlmow_modelbuilder/ModelBuilder.py
otlmow_modelbuilder/NewOTLBaseClassNotImplemented.py
otlmow_modelbuilder/OSLOCollector.py
otlmow_modelbuilder/OSLOInMemoryCreator.py
otlmow_modelbuilder/OTLClassCreator.py
otlmow_modelbuilder/OTLComplexDatatypeCreator.py
otlmow_modelbuilder/OTLEnumerationCreator.py
otlmow_modelbuilder/OTLExtraChecker.py
otlmow_modelbuilder/OTLModelCreator.py
otlmow_modelbuilder/OTLPrimitiveDatatypeCreator.py
otlmow_modelbuilder/OTLUnionDatatypeCreator.py
otlmow_modelbuilder/SettingsManager.py
otlmow_modelbuilder/__init__.py
otlmow_modelbuilder/legacy_types.csv
otlmow_modelbuilder/main.py
otlmow_modelbuilder/settings_otlmow_modelbuilder.json
otlmow_modelbuilder/Exceptions/NestedListAttributeError.py
otlmow_modelbuilder/SQLDataClasses/GeneralInfoRecord.py
otlmow_modelbuilder/SQLDataClasses/Inheritance.py
otlmow_modelbuilder/SQLDataClasses/OSLOAttribuut.py
otlmow_modelbuilder/SQLDataClasses/OSLOClass.py
otlmow_modelbuilder/SQLDataClasses/OSLODatatypeComplex.py
otlmow_modelbuilder/SQLDataClasses/OSLODatatypeComplexAttribuut.py
otlmow_modelbuilder/SQLDataClasses/OSLODatatypePrimitive.py
otlmow_modelbuilder/SQLDataClasses/OSLODatatypePrimitiveAttribuut.py
otlmow_modelbuilder/SQLDataClasses/OSLODatatypeUnion.py
otlmow_modelbuilder/SQLDataClasses/OSLODatatypeUnionAttribuut.py
otlmow_modelbuilder/SQLDataClasses/OSLOEnumeration.py
otlmow_modelbuilder/SQLDataClasses/OSLORelatie.py
otlmow_modelbuilder/SQLDataClasses/OSLOTypeLink.py
otlmow_modelbuilder/SQLDataClasses/__init__.py
otlmow_modelbuilder-0.42.dist-info/licenses/LICENSE
otlmow_modelbuilder-0.42.dist-info/METADATA
otlmow_modelbuilder-0.42.dist-info/WHEEL
otlmow_modelbuilder-0.42.dist-info/top_level.txt
otlmow_modelbuilder-0.42.dist-info/RECORD
