Metadata-Version: 2.4
Name: otlmow_modelbuilder
Version: 0.42
Author-email: David Vlaminck <david.vlaminck@mow.vlaanderen.be>
License:                     GNU GENERAL PUBLIC LICENSE
Project-URL: Homepage, https://github.com/davidvlaminck/OTLMOW-ModelBuilder
Project-URL: Bug Tracker, https://github.com/davidvlaminck/OTLMOW-ModelBuilder/issues
Classifier: Programming Language :: Python :: 3
Classifier: Programming Language :: Python :: 3.9
Classifier: Programming Language :: Python :: 3.10
Classifier: Programming Language :: Python :: 3.11
Classifier: Programming Language :: Python :: 3.12
Classifier: Programming Language :: Python :: 3.13
Classifier: Programming Language :: Python :: 3.14
Classifier: Operating System :: OS Independent
Requires-Python: >=3.9
License-File: LICENSE
Requires-Dist: rdflib>=6.0.0
Requires-Dist: tqdm>=4.66.1
Provides-Extra: test
Requires-Dist: pytest; extra == "test"
Requires-Dist: pytest-cov; extra == "test"
Requires-Dist: pytest-subtests; extra == "test"
Requires-Dist: pytest-timeout; extra == "test"
Requires-Dist: nbmake; extra == "test"
Dynamic: license-file
